UzbekNLP/Tokenizer.py
UzbekNLP/__init__.py
UzbekNLP-0.0.2.dist-info/LICENSE
UzbekNLP-0.0.2.dist-info/METADATA
UzbekNLP-0.0.2.dist-info/WHEEL
UzbekNLP-0.0.2.dist-info/top_level.txt
UzbekNLP-0.0.2.dist-info/RECORD
